qt_niu/__init__.py
qt_niu/collapsible_widget.py
qt_niu/dialog.py
qt_niu/interaction.py
qt_niu/table.py
qt_niu-0.1.0.dist-info/LICENSE
qt_niu-0.1.0.dist-info/METADATA
qt_niu-0.1.0.dist-info/WHEEL
qt_niu-0.1.0.dist-info/top_level.txt
qt_niu-0.1.0.dist-info/RECORD
