Metadata-Version: 2.2
Name: qt-niu
Version: 0.1.0
Summary: Reusable Qt elements
Author-email: Adam Tyson <code@adamltyson.com>
License: MIT
Project-URL: Homepage, https://github.com/neuroinformatics-unit/qt-niu
Project-URL: Bug Tracker, https://github.com/neuroinformatics-unit/qt-niu/issues
Project-URL: Documentation, https://github.com/neuroinformatics-unit/qt-niu
Project-URL: Source Code, https://github.com/neuroinformatics-unit/qt-niu
Project-URL: User Support, https://github.com/neuroinformatics-unit/qt-niu/issues
Classifier: Development Status :: 2 - Pre-Alpha
Classifier: Programming Language :: Python
Classifier: Programming Language :: Python :: 3
Classifier: Programming Language :: Python :: 3.11
Classifier: Programming Language :: Python :: 3.12
Classifier: Programming Language :: Python :: 3.13
Classifier: Operating System :: OS Independent
Classifier: License :: OSI Approved :: MIT License
Requires-Python: >=3.11.0
License-File: LICENSE
Requires-Dist: qtpy
Requires-Dist: superqt
Requires-Dist: pandas
Provides-Extra: dev
Requires-Dist: pytest; extra == "dev"
Requires-Dist: pytest-cov; extra == "dev"
Requires-Dist: pytest-qt; extra == "dev"
Requires-Dist: coverage; extra == "dev"
Requires-Dist: tox; extra == "dev"
Requires-Dist: mypy; extra == "dev"
Requires-Dist: pre-commit; extra == "dev"
Requires-Dist: ruff; extra == "dev"
Requires-Dist: setuptools_scm; extra == "dev"
Requires-Dist: pyqt5; extra == "dev"
